{"type":"FeatureCollection","features":[{"type":"Feature","properties":{"NOMBRE":"Takul"},"geometry":{"type":"Point","coordinates":[-86.780071,21.14393]}},{"type":"Feature","properties":{"NOMBRE":"La Duna (San Pablo)"},"geometry":{"type":"Point","coordinates":[-86.78369,21.05338]}},{"type":"Feature","properties":{"NOMBRE":"Ni'ku"},"geometry":{"type":"Point","coordinates":[-86.747795,21.13469]}},{"type":"Feature","properties":{"NOMBRE":"Pok ta pok"},"geometry":{"type":"Point","coordinates":[-86.760432,21.131924]}}]}